aaaamcpuser/__init__.py
aaaamcpuser/__main__.py
aaaamcpuser/main.py
aaaamcpuser1-0.1.0.dist-info/METADATA
aaaamcpuser1-0.1.0.dist-info/WHEEL
aaaamcpuser1-0.1.0.dist-info/entry_points.txt
aaaamcpuser1-0.1.0.dist-info/top_level.txt
aaaamcpuser1-0.1.0.dist-info/RECORD
